GreenPonik_SHT40/SHT40.py
GreenPonik_SHT40/__init__.py
tests/__init__.py
tests/test_SHT40.py
greenponik_sht40-0.0.1.dist-info/METADATA
greenponik_sht40-0.0.1.dist-info/WHEEL
greenponik_sht40-0.0.1.dist-info/top_level.txt
greenponik_sht40-0.0.1.dist-info/RECORD
