Metadata-Version: 2.1
Name: greenponik-sht40
Version: 0.0.1
Summary: Read SHT40 through Python3 on raspberry pi
Home-page: https://github.com/GreenPonik/GreenPonik_SHT40
Author: GreenPonik SAS
Author-email: contact@greenponik.com
License: MIT
Project-URL: Source, https://github.com/GreenPonik/GreenPonik_SHT40/
Project-URL: Bug Reports, https://github.com/GreenPonik/GreenPonik_SHT40/issues
Keywords: GreenPonik hydroponics sht40     light reader python hardware diy iot raspberry pi
Platform: UNKNOWN
Classifier: Programming Language :: Python :: 3
Classifier: License :: OSI Approved :: MIT License
Classifier: Operating System :: OS Independent
Requires-Python: >=3.7.0
Requires-Dist: adafruit-blinka
Requires-Dist: adafruit-circuitpython-sht4x
Requires-Dist: adafruit-extended-bus
